Workbook

Sheet All_Tickets
A1: (Do Not Modify) Case | B1: (Do Not Modify) Row Checksum | C1: (Do Not Modify) Modified On | D1: Case Number | E1: Customer Name (Customer) (Account) | F1: Contact | G1: Created On | H1: Case Title | I1: Support Agent | J1: Status Reason | K1: Priority | L1: Country (Customer) (Account) | M1: Billable Duration | N1: Updated On | O1: Total Days | P1: Comments
A2: dd140b0f-6fd9-42d8-a0c7-a547a0458d37 | B2: uZZwAjFOnTk8jDbcD9xoROkx12E/3ezkzUSTYoYsGhUGGq9krTTSsg7mpPKBVCoBx2ze0lYcBwsyoe4dhOhuTw== | C2: 46071.84 | D2: DS-73092-D1Z1 | E2: Q4 Services Inc. | F2: Berta Alday | G2: 46069.338 | H2: Job Task Dimension error | I2: Swaraj Kalsi | J2: Closed | K2: Normal - P2 | L2: USA | M2: 1 | N2: 46072 | O2: =IF(J2="Closed", N2-G2+1, TODAY()-G2+1) -> 3.6616088 | P2: Closed
A3: ccdea6df-0b36-499a-99c4-f6e7d105dd8e | B3: OkTkuXrDTizIf/rMKPviziisvIBxsIYRhPLu29pt5WHdaAxjR703Bea22iKUeFEipAMCKc9u/MSK6zTCO4XeJA== | C3: 46071.776 | D3: DS-72756-M1Y0 | E3: Step by Step INC. | F3: Cynthia Sherrill | G3: 46065.648 | H3: Admin change notice BC | I3: Nikita Bhosale | J3: Closed | K3: Normal - P2 | L3: USA | M3: 0.5 | N3: 46073 | O3: =IF(J3="Closed", N3-G3+1, TODAY()-G3+1) -> 8.3517014 | P3: Closed
A4: 0ccc5dce-d405-f111-8406-6045bd1fb4f5 | B4: cPUrPyMvcde9TtfWXe5Og3BauJmJyiSQByit6AKTtVd0QD5swdUv4uMJbPa+MgBrz7UIZWOHfttcTR3LfZEIJA== | C4: 46071.819 | D4: DS-72204-J5G0 | E4: Franken Solar | F4: Steve Bachand | G4: 46062.689 | H4: FW: Alert! We've disabled one of your flows | I4: Divya Goyal | J4: In Progress | K4: Normal - P2 | L4: Canada | N4: 46096 | O4: =IF(J4="Closed", N4-G4+1, TODAY()-G4+1) -> 34.311285 | P4: Mircosoft needs time
A5: 3b881f72-2e01-f111-8407-6045bd1d66c6 | B5: nPoRIyv9TBQ7aWhghqQLpCbUIZvZrasLACXSvp9u/rUt3xN49vlFTwvI5cHorAC+qWZYkRt661CHZR5YaOJIww== | C5: 46071.779 | D5: DS-71652-B6P1 | E5: Summit Net Trekker | F5: Tania Kopystianskyj | G5: 46056.771 | H5: help closing fiscal year | I5: Swaraj Kalsi | J5: Closed | K5: Normal - P2 | L5: USA | M5: 0 | N5: 46079 | O5: =IF(J5="Closed", N5-G5+1, TODAY()-G5+1) -> 23.228576 | P5: Closed
A6: dfeab9b3-acfb-f011-8406-6045bd1d6d98 | B6: OENyslksEpf5tXXD7yAJ/tZsBnOCdfunJoYVU7V/xGexRt/S046SAF3qrCqs1fBydTm2KNHstlk+qXcsdjsmxg== | C6: 46071.776 | D6: DS-71142-T5B7 | E6: Jedwards International, Inc. | F6: Rich Hanson | G6: 46049.763 | H6: Trello NV202 Development Environment cannot find sql server | I6: Suresh Miglani(Freelancer) | J6: Closed | K6: Normal - P2 | L6: USA | M6: 7 | N6: 46076 | O6: =IF(J6="Closed", N6-G6+1, TODAY()-G6+1) -> 27.236528 | P6: Closed
A7: 171c8208-b605-4e7e-981a-8bcf9adccd75 | B7: S1N3DdFfOUwhlaSnvWxfbuknYm08ofskfe78epkl9s7j7Y9yFGmBMxFBmAZbTNBxLAPNjIpkfghMHSatSGiGBQ== | C7: 46071.857 | D7: DS-70134-G6T7 | E7: Iridex Corporation | F7: Brian Yates | G7: 46037.589 | H7: Dynamic Square Bin Content All Items Template Request | I7: Jay Desai | J7: Closed | K7: Normal - P2 | L7: USA | M7: 7 | N7: 46079 | O7: =IF(J7="Closed", N7-G7+1, TODAY()-G7+1) -> 42.4111 | P7: Closed
A8: 3cbbfc2c-17f2-f011-8406-7ced8de5aca4 | B8: hiPDv4oUGjzBf5raL8FM+hsHKX6IZsC4l7FtpozbVsHspHD9Qfv3DtDfGK4JBljXrTgW2HMmQN3YGFRVBi6bqA== | C8: 46071.834 | D8: DS-70132-J5X0 | E8: Summit Net Trekker | F8: Tania Kopystianskyj | G8: 46037.567 | H8: RE: 2025 Business central questions | I8: Swaraj Kalsi | J8: Closed | K8: Normal - P2 | L8: USA | M8: 3 | N8: 46076 | O8: =IF(J8="Closed", N8-G8+1, TODAY()-G8+1) -> 39.433056 | P8: Closed
A9: 398909f0-47cc-49d5-8493-12df2f15d7b7 | B9: +ZTcKKJ+NR5g7++kozgP2oF9RNVl1J3id2mYIwD2uOrsKWsqiF5MkJGS2g+8FV0AzWUkad4T0S6/Tlt/3nxg1Q== | C9: 46071.838 | D9: DS-68839-W7K0 | E9: Iridex Corporation | F9: Brian Yates | G9: 46021.65 | H9: Generating cycle count tags | I9: Jay Desai | J9: Closed | K9: Normal - P2 | L9: USA | M9: 2.75 | N9: 46079 | O9: =IF(J9="Closed", N9-G9+1, TODAY()-G9+1) -> 58.350255 | P9: Closed
A10: fcd95596-c167-4cf2-89a8-57e90af488de | B10: IjFyvXm+jL/KvuZEHZk8ObwPamCCtSB2c0vBwwcnKKZeefz8/TY4qqljI5R+PsIE5+3v9Cf3fVNHCMpuEmlUHw== | C10: 46071.834 | D10: DS-68764-C7G5 | E10: Scottish Rite of Freemasonry | F10: Jorge Franchi | G10: 46020.43 | H10: Format change of file download | I10: Swaraj Kalsi | J10: In Progress | K10: Normal - P2 | L10: USA | N10: 46093 | O10: =IF(J10="Closed", N10-G10+1, TODAY()-G10+1) -> 76.569838 | P10: Client sent some more changes
A11: 777a4d45-8778-4732-ab13-79057c3f98a0 | B11: dmbAGgxdB9pTb+oTYdF/WL4dtVU28SVaItAU+3IKbDaZrssruM+20tMMxHEeOe5ahsXXqs2bet1747ZsZil7qA== | C11: 46071.86 | D11: DS-68389-P5S3 | E11: Mexi Land Inc | F11: Anthony Candelario | G11: 46009.645 | H11: Printer selections page | I11: Swaraj Kalsi | J11: Closed | K11: Normal - P2 | L11: USA | M11: 1.5 | N11: 46080 | O11: =IF(J11="Closed", N11-G11+1, TODAY()-G11+1) -> 71.355428 | P11: Closed
A12: 9b03d0cc-6138-478f-b0fa-51817c02836a | B12: 13ez45sQOsqmHs3ICb4rB/77avabEPR0pGktU2KNKBcASi0nWQF2sSFAHzNfPv+psG52/WXBDqf1F34xqsq+OA== | C12: 46071.862 | D12: DS-66177-F3F1 | E12: Iridex Corporation | F12: Brian Yates | G12: 45986.34 | H12: DS // BC // MRP // NEED ROOT CAUSE ANALYSIS // 112425 | I12: Shreyansh Gupta | J12: In Progress | K12: Normal - P2 | L12: USA | M12: 6 | N12: 46093 | O12: =IF(J12="Closed", N12-G12+1, TODAY()-G12+1) -> 110.65986 | P12: Some more changes needed - Jay is working on it
A13: c460973f-d3c3-f011-bbd3-000d3aa052bf | B13: eCQgLs0+orKdt/PEKN10j+fYkw1sn/iDu9qKQSzC1cYIvxh6oUmv/IIvINh8JNnxwyorqzhQ+97znrJGuXQV1g== | C13: 46071.831 | D13: DS-65512-R3W2 | E13: Truecare Biomedix | F13: Rossanna Vanegas | G13: 45978.691 | H13: API Addition - Shipment Method fields | I13: Swaraj Kalsi | J13: Closed | K13: Normal - P2 | L13: USA | M13: 7.5 | N13: 46072 | O13: =IF(J13="Closed", N13-G13+1, TODAY()-G13+1) -> 94.309491 | P13: Closed
D14: DS-73464-G6W1 | E14: Step by Step INC. | F14: Daniel Ripa | G14: 46071.845 | H14: RE: Your environment Sandbox_13Dec2024 could not be updated | I14: Nikita Bhosale | J14: Closed | K14: Normal - P2 | L14: USA | M14: 0 | N14: 46080 | O14: =IF(J14="Closed", N14-G14+1, TODAY()-G14+1) -> 9.1548611 | P14: Closed
D15: DS-72640-M9Z0 | E15: Q4 Services Inc. | F15: Berta Alday | G15: 46064 | H15: Q4 Services - PO25-0977 | I15: Swaraj Kalsi | J15: Closed | K15: Normal - P2 | L15: USA | M15: 1 | N15: 46066 | O15: =IF(J15="Closed", N15-G15+1, TODAY()-G15+1) -> 3 | P15: Closed
D16: DS-72998-K3C5 | E16: Iridex Corporation | F16: Brian Yates | G16: 46066 | H16: Sales Order Not Calculating Sales Tax | I16: Swaraj Kalsi | J16: Closed | K16: Normal - P2 | L16: USA | M16: 1.5 | N16: 46071 | O16: =IF(J16="Closed", N16-G16+1, TODAY()-G16+1) -> 6 | P16: Closed
D17: DS-73731-B5W8 | E17: Iridex Corporation | F17: Brian Yates | G17: 46073.328 | H17: Jet Report runs and never completes. May need fixing. Jet Report for acct# 2021 | I17: Jay Desai | J17: Closed | K17: Normal - P2 | L17: USA | M17: 0 | N17: 46079 | O17: =IF(J17="Closed", N17-G17+1, TODAY()-G17+1) -> 6.6722222 | P17: Closed
D18: DS-74014-V7H5 | E18: Franken Solar | F18: Steve Bachand | G18: 46077.923 | H18: FW: Modify your extension so it’s compatible with the version 27.5.46631.0 | J18: Closed | L18: Canada | M18: 0 | N18: 46079 | O18: =IF(J18="Closed", N18-G18+1, TODAY()-G18+1) -> 2.0770833 | P18: Closed
D19: DS-74263-F9W5 | E19: Iridex Corporation | F19: Brian Yates | G19: 46079.381 | H19: Trended Spending Report By Department By Account - Reopen | I19: Jay Desai | J19: In Progress | K19: Normal - P2 | L19: USA | N19: 46093 | O19: =IF(J19="Closed", N19-G19+1, TODAY()-G19+1) -> 17.619444 | P19: Jay will close this soon
D20: DS-74408-Z5Z0 | E20: Iridex Corporation | F20: Brian Yates | G20: 46080.463 | H20: Purchase order archives modifications if possible | I20: Swaraj Kalsi | J20: In Progress | K20: Normal - P2 | L20: USA | M20: 3 | N20: 46094 | O20: =IF(J20="Closed", N20-G20+1, TODAY()-G20+1) -> 16.5375 | P20: Hours approved and It will live by Monday
D21: DS-74582-C7X1 | E21: Centon Electronics | F21: Jennifer Miscione | G21: 46083.359 | H21: DS-59295-Z2X0: Split Sales Line Issue | I21: Swaraj Kalsi | J21: In Progress | K21: Normal - P2 | L21: USA | N21: 46093 | O21: =IF(J21="Closed", N21-G21+1, TODAY()-G21+1) -> 13.640972 | P21: Login issues going with client
D22: DS-74933-H7J6 | E22: Aline Studio | F22: LINDSEY BEDNAR | G22: 46084.826 | H22: ALine support request - turn off auto contact adding + fix time zone | I22: Sahil Bhaldar | J22: Closed | K22: Normal - P2 | L22: USA | M22: 0.75 | N22: 46085 | O22: =IF(J22="Closed", N22-G22+1, TODAY()-G22+1) -> 1.1743056
D23: DS-75008-X2M9 | E23: Iridex Corporation | F23: Brian Yates | G23: 46085.878 | H23: Need Swaraj to examine DEV sandbox dynamic Square extensions to make sure they are all there | I23: Swaraj Kalsi | J23: In Progress | K23: Normal - P2 | L23: USA | M23: 1 | N23: 46094 | O23: =IF(J23="Closed", N23-G23+1, TODAY()-G23+1) -> 11.121528 | P23: Environment update done successfully
D24: DS-75005-Y9B1 | E24: Aline Studio | F24: LINDSEY BEDNAR | G24: 46085.774 | H24: ALine Support Request - Dynamics Errors + Customizations March 4, 2026 | I24: Sahil Bhaldar | J24: In Progress | K24: Normal - P2 | L24: USA | N24: 46093 | O24: =IF(J24="Closed", N24-G24+1, TODAY()-G24+1) -> 11.225694 | P24: Ticket raised to Mircrosoft support
D25: DS-75059-H4P6 | E25: Truecare Biomedix | F25: Narayan Raj | G25: 46086.363 | H25: Packing slip needs an urgent correction | I25: Swaraj Kalsi | J25: Closed | K25: Normal - P2 | L25: USA | M25: 1 | N25: 46087 | O25: =IF(J25="Closed", N25-G25+1, TODAY()-G25+1) -> 1.6375 | P25: Closed
D26: DS-75098-J7R0 | E26: Iridex Corporation | F26: Brian Yates | G26: 46086.684 | H26: New Supplier // REPUBLIC OF THE MARSHALL ISLANDS // 030326 | I26: Swaraj Kalsi | J26: Closed | K26: Normal - P2 | L26: USA | M26: 1 | N26: 46086 | O26: =IF(J26="Closed", N26-G26+1, TODAY()-G26+1) -> 0.31597222 | P26: Closed
D27: DS-75092-S1Q4 | E27: TAT Technologies | F27: Kim VU | G27: 46086.661 | H27: ACH Export | I27: Swaraj Kalsi | J27: In Progress | K27: Normal - P2 | L27: USA | M27: 12 | N27: 46093 | O27: =IF(J27="Closed", N27-G27+1, TODAY()-G27+1) -> 10.338889 | P27: Effort approved and after that we can start working on it
D28: DS-75472-D4V2 | E28: Van Dolder's Home Team | F28: Marty Tengelis | G28: 46090.522 | H28: Sales ORder not updating | I28: Swaraj Kalsi | J28: Closed | K28: Normal - P2 | L28: Canada | M28: 1 | N28: 46094 | O28: =IF(J28="Closed", N28-G28+1, TODAY()-G28+1) -> 4.4784722 | P28: Closed
D29: DS-75601-D9L7 | E29: Step by Step INC. | F29: Daniel Ripa | G29: 46091.607 | H29: Modify your extension so it’s compatible with the version 28.0.46665.47371 | I29: Shubham Singh | J29: In Progress | K29: Normal - P2 | L29: USA | N29: 46093 | O29: =IF(J29="Closed", N29-G29+1, TODAY()-G29+1) -> 5.3930556 | P29: Work done and sent for client tetsing
D30: DS-75591-S5C1 | E30: Mexi Land Inc | F30: Anthony Candelario | G30: 46091.526 | H30: System addition | I30: Swaraj Kalsi | J30: In Progress | K30: Normal - P2 | L30: USA | N30: 46093 | O30: =IF(J30="Closed", N30-G30+1, TODAY()-G30+1) -> 5.4743056 | P30: Swaraj will complete this by tomorrow
D31: DS-75555-W0M7 | E31: Truecare Biomedix | F31: Narayan Raj | G31: 46091.385 | H31: Post Shipment Schafer button - request new feature | I31: Akshay Thakkar | J31: In Progress | K31: Normal - P2 | L31: USA | N31: 46093 | O31: =IF(J31="Closed", N31-G31+1, TODAY()-G31+1) -> 5.6152778 | P31: Developed the changes in sandbox and ask for a meeting with client
D32: DS-75607-W7R7 | E32: Truecare Biomedix | F32: Rossanna Vanegas | G32: 46091.635 | H32: Urgent Request: Unlock UOM Titles on Posted Sales Invoices (Production Environment) | I32: Swaraj Kalsi | J32: Closed | K32: Normal - P2 | L32: USA | M32: 2.5 | N32: 46092 | O32: =IF(J32="Closed", N32-G32+1, TODAY()-G32+1) -> 1.3652778 | P32: Closed
D33: DS-75768-X3G8 | E33: Iridex Corporation | F33: Brian Yates | G33: 46092.744 | H33: Jet Report not working | I33: Jay Desai | J33: In Progress | K33: Normal - P2 | L33: USA | N33: 46093 | O33: =IF(J33="Closed", N33-G33+1, TODAY()-G33+1) -> 4.2555556 | P33: Jay is working on it
D34: DS-75774-F0F6 | E34: TAT Technologies | F34: Kim VU | G34: 46092.767 | H34: Approval Workflow for Recurring Journal Entries | I34: Swaraj Kalsi | J34: In Progress | K34: Normal - P2 | L34: USA | N34: 46093 | O34: =IF(J34="Closed", N34-G34+1, TODAY()-G34+1) -> 4.2326389 | P34: Swaraj is working on it
D35: DS-75949-Q8W3 | E35: Iridex Corporation | F35: Brian Yates | G35: 46094.372 | H35: Hung up and ask user to log back instead of just refreshing | I35: Swaraj Kalsi | J35: In Progress | K35: Normal - P2 | L35: USA | M35: 1 | N35: 46094 | O35: =IF(J35="Closed", N35-G35+1, TODAY()-G35+1) -> 2.6277778 | P35: Work done and sent for client tetsing

Sheet Close_Tickets
A1: Case Number | B1: Customer Name (Customer) (Account) | C1: Contact | D1: Created On | E1: Case Title | F1: Support Agent | G1: Status Reason | H1: Priority | I1: Country (Customer) (Account) | J1: Billable Duration | K1: Updated On | L1: Total Days | M1: Comments
A2: {=_xlfn._xlws.FILTER(All_Tickets!D:O, All_Tickets!J:J="Closed", "No Closed Tickets")} -> DS-73092-D1Z1 | B2: Q4 Services Inc. | C2: Berta Alday | D2: 46069.338 | E2: Job Task Dimension error | F2: Swaraj Kalsi | G2: Closed | H2: Normal - P2 | I2: USA | J2: 1 | K2: 46072 | L2: 3.6616088
A3: DS-72756-M1Y0 | B3: Step by Step INC. | C3: Cynthia Sherrill | D3: 46065.648 | E3: Admin change notice BC | F3: Nikita Bhosale | G3: Closed | H3: Normal - P2 | I3: USA | J3: 0.5 | K3: 46073 | L3: 8.3517014
A4: DS-71652-B6P1 | B4: Summit Net Trekker | C4: Tania Kopystianskyj | D4: 46056.771 | E4: help closing fiscal year | F4: Swaraj Kalsi | G4: Closed | H4: Normal - P2 | I4: USA | J4: 0 | K4: 46079 | L4: 23.228576
A5: DS-71142-T5B7 | B5: Jedwards International, Inc. | C5: Rich Hanson | D5: 46049.763 | E5: Trello NV202 Development Environment cannot find sql server | F5: Suresh Miglani(Freelancer) | G5: Closed | H5: Normal - P2 | I5: USA | J5: 7 | K5: 46076 | L5: 27.236528
A6: DS-70134-G6T7 | B6: Iridex Corporation | C6: Brian Yates | D6: 46037.589 | E6: Dynamic Square Bin Content All Items Template Request | F6: Jay Desai | G6: Closed | H6: Normal - P2 | I6: USA | J6: 7 | K6: 46079 | L6: 42.4111
A7: DS-70132-J5X0 | B7: Summit Net Trekker | C7: Tania Kopystianskyj | D7: 46037.567 | E7: RE: 2025 Business central questions | F7: Swaraj Kalsi | G7: Closed | H7: Normal - P2 | I7: USA | J7: 3 | K7: 46076 | L7: 39.433056
A8: DS-68839-W7K0 | B8: Iridex Corporation | C8: Brian Yates | D8: 46021.65 | E8: Generating cycle count tags | F8: Jay Desai | G8: Closed | H8: Normal - P2 | I8: USA | J8: 2.75 | K8: 46079 | L8: 58.350255
A9: DS-68389-P5S3 | B9: Mexi Land Inc | C9: Anthony Candelario | D9: 46009.645 | E9: Printer selections page | F9: Swaraj Kalsi | G9: Closed | H9: Normal - P2 | I9: USA | J9: 1.5 | K9: 46080 | L9: 71.355428
A10: DS-65512-R3W2 | B10: Truecare Biomedix | C10: Rossanna Vanegas | D10: 45978.691 | E10: API Addition - Shipment Method fields | F10: Swaraj Kalsi | G10: Closed | H10: Normal - P2 | I10: USA | J10: 7.5 | K10: 46072 | L10: 94.309491
A11: DS-73464-G6W1 | B11: Step by Step INC. | C11: Daniel Ripa | D11: 46071.845 | E11: RE: Your environment Sandbox_13Dec2024 could not be updated | F11: Nikita Bhosale | G11: Closed | H11: Normal - P2 | I11: USA | J11: 0 | K11: 46080 | L11: 9.1548611
A12: DS-72640-M9Z0 | B12: Q4 Services Inc. | C12: Berta Alday | D12: 46064 | E12: Q4 Services - PO25-0977 | F12: Swaraj Kalsi | G12: Closed | H12: Normal - P2 | I12: USA | J12: 1 | K12: 46066 | L12: 3
A13: DS-72998-K3C5 | B13: Iridex Corporation | C13: Brian Yates | D13: 46066 | E13: Sales Order Not Calculating Sales Tax | F13: Swaraj Kalsi | G13: Closed | H13: Normal - P2 | I13: USA | J13: 1.5 | K13: 46071 | L13: 6
A14: DS-73731-B5W8 | B14: Iridex Corporation | C14: Brian Yates | D14: 46073.328 | E14: Jet Report runs and never completes. May need fixing. Jet Report for acct# 2021 | F14: Jay Desai | G14: Closed | H14: Normal - P2 | I14: USA | J14: 0 | K14: 46079 | L14: 6.6722222
A15: DS-74014-V7H5 | B15: Franken Solar | C15: Steve Bachand | D15: 46077.923 | E15: FW: Modify your extension so it’s compatible with the version 27.5.46631.0 | F15: 0 | G15: Closed | H15: 0 | I15: Canada | J15: 0 | K15: 46079 | L15: 2.0770833
A16: DS-74933-H7J6 | B16: Aline Studio | C16: LINDSEY BEDNAR | D16: 46084.826 | E16: ALine support request - turn off auto contact adding + fix time zone | F16: Sahil Bhaldar | G16: Closed | H16: Normal - P2 | I16: USA | J16: 0.75 | K16: 46085 | L16: 1.1743056
A17: DS-75059-H4P6 | B17: Truecare Biomedix | C17: Narayan Raj | D17: 46086.363 | E17: Packing slip needs an urgent correction | F17: Swaraj Kalsi | G17: Closed | H17: Normal - P2 | I17: USA | J17: 1 | K17: 46087 | L17: 1.6375
A18: DS-75098-J7R0 | B18: Iridex Corporation | C18: Brian Yates | D18: 46086.684 | E18: New Supplier // REPUBLIC OF THE MARSHALL ISLANDS // 030326 | F18: Swaraj Kalsi | G18: Closed | H18: Normal - P2 | I18: USA | J18: 1 | K18: 46086 | L18: 0.31597222
A19: DS-75472-D4V2 | B19: Van Dolder's Home Team | C19: Marty Tengelis | D19: 46090.522 | E19: Sales ORder not updating | F19: Swaraj Kalsi | G19: Closed | H19: Normal - P2 | I19: Canada | J19: 1 | K19: 46094 | L19: 4.4784722
A20: DS-75607-W7R7 | B20: Truecare Biomedix | C20: Rossanna Vanegas | D20: 46091.635 | E20: Urgent Request: Unlock UOM Titles on Posted Sales Invoices (Production Environment) | F20: Swaraj Kalsi | G20: Closed | H20: Normal - P2 | I20: USA | J20: 2.5 | K20: 46092 | L20: 1.3652778

Sheet Balance Hours
A1: Account Name | B1: December | C1: January | D1: Febuary | E1: March
A2: Americal Vision Group | B2: 47 | C2: 47 | D2: 47 | E2: =D2-SUMIFS(All_Tickets!M:M, All_Tickets!E:E, A2, All_Tickets!J:J, "Closed", All_Tickets!N:N, ">="&EOMONTH(TODAY(),-1)+1, All_Tickets!N:N, "<="&EOMONTH(TODAY(),0)) -> 47
A3: Anderson and Middleton | B3: 24.5 | C3: 24.5 | D3: 24.5 | E3: =D3-SUMIFS(All_Tickets!M:M, All_Tickets!E:E, A3, All_Tickets!J:J, "Closed", All_Tickets!N:N, ">="&EOMONTH(TODAY(),-1)+1, All_Tickets!N:N, "<="&EOMONTH(TODAY(),0)) -> 24.5
A4: Bahai's Canada | B4: 24 | C4: 24 | D4: 24 | E4: =D4-SUMIFS(All_Tickets!M:M, All_Tickets!E:E, A4, All_Tickets!J:J, "Closed", All_Tickets!N:N, ">="&EOMONTH(TODAY(),-1)+1, All_Tickets!N:N, "<="&EOMONTH(TODAY(),0)) -> 24
A5: Buckland | B5: 46.5 | C5: 46.5 | D5: 46.5 | E5: =D5-SUMIFS(All_Tickets!M:M, All_Tickets!E:E, A5, All_Tickets!J:J, "Closed", All_Tickets!N:N, ">="&EOMONTH(TODAY(),-1)+1, All_Tickets!N:N, "<="&EOMONTH(TODAY(),0)) -> 46.5
A6: Centon Electronics | B6: 35.5 | C6: 35.5 | D6: 35.5 | E6: =D6-SUMIFS(All_Tickets!M:M, All_Tickets!E:E, A6, All_Tickets!J:J, "Closed", All_Tickets!N:N, ">="&EOMONTH(TODAY(),-1)+1, All_Tickets!N:N, "<="&EOMONTH(TODAY(),0)) -> 35.5
A7: Child development | B7: 51.75 + 6.5 | C7: 51.75 + 6.5 | D7: 51.75 + (-15) | E7: 51.75 + 10
A8: F&H Group USA Inc. | B8: 21.5 | C8: 20.5 | D8: 20.5 | E8: =D8-SUMIFS(All_Tickets!M:M, All_Tickets!E:E, A8, All_Tickets!J:J, "Closed", All_Tickets!N:N, ">="&EOMONTH(TODAY(),-1)+1, All_Tickets!N:N, "<="&EOMONTH(TODAY(),0)) -> 20.5
A9: Franken Solar | B9: 4 | C9: 4 | D9: 3 | E9: =D9-SUMIFS(All_Tickets!M:M, All_Tickets!E:E, A9, All_Tickets!J:J, "Closed", All_Tickets!N:N, ">="&EOMONTH(TODAY(),-1)+1, All_Tickets!N:N, "<="&EOMONTH(TODAY(),0)) -> 3
A10: Griffin Glass | B10: 13.5 | C10: 13.5 | D10: 13.5 | E10: =D10-SUMIFS(All_Tickets!M:M, All_Tickets!E:E, A10, All_Tickets!J:J, "Closed", All_Tickets!N:N, ">="&EOMONTH(TODAY(),-1)+1, All_Tickets!N:N, "<="&EOMONTH(TODAY(),0)) -> 13.5
A11: Iridex Corporation | B11: 34.8 | C11: 26.8 | D11: 12.05 | E11: =D11-SUMIFS(All_Tickets!M:M, All_Tickets!E:E, A11, All_Tickets!J:J, "Closed", All_Tickets!N:N, ">="&EOMONTH(TODAY(),-1)+1, All_Tickets!N:N, "<="&EOMONTH(TODAY(),0)) -> 11.05
A12: Jedwards International, Inc. | B12: 28.25 | C12: 25.25 | D12: 18.25 | E12: =D12-SUMIFS(All_Tickets!M:M, All_Tickets!E:E, A12, All_Tickets!J:J, "Closed", All_Tickets!N:N, ">="&EOMONTH(TODAY(),-1)+1, All_Tickets!N:N, "<="&EOMONTH(TODAY(),0)) -> 18.25
A13: Mexi Land Inc | B13: 52.5 | C13: 52.5 | D13: 51 | E13: =D13-SUMIFS(All_Tickets!M:M, All_Tickets!E:E, A13, All_Tickets!J:J, "Closed", All_Tickets!N:N, ">="&EOMONTH(TODAY(),-1)+1, All_Tickets!N:N, "<="&EOMONTH(TODAY(),0)) -> 51
A14: Microboards Technology | B14: 14.5 | C14: 14.5 | D14: 14.5 | E14: =D14-SUMIFS(All_Tickets!M:M, All_Tickets!E:E, A14, All_Tickets!J:J, "Closed", All_Tickets!N:N, ">="&EOMONTH(TODAY(),-1)+1, All_Tickets!N:N, "<="&EOMONTH(TODAY(),0)) -> 14.5
A15: Millcreek Inn | B15: 9.5 | C15: 9.5 | D15: 8.5 | E15: =D15-SUMIFS(All_Tickets!M:M, All_Tickets!E:E, A15, All_Tickets!J:J, "Closed", All_Tickets!N:N, ">="&EOMONTH(TODAY(),-1)+1, All_Tickets!N:N, "<="&EOMONTH(TODAY(),0)) -> 8.5
A16: Q4 Services Inc. | B16: 47 | C16: 47 | D16: 44 | E16: =D16-SUMIFS(All_Tickets!M:M, All_Tickets!E:E, A16, All_Tickets!J:J, "Closed", All_Tickets!N:N, ">="&EOMONTH(TODAY(),-1)+1, All_Tickets!N:N, "<="&EOMONTH(TODAY(),0)) -> 44
A17: Step by Step INC. | B17: 30.5 | C17: 29 | D17: 27 | E17: =D17-SUMIFS(All_Tickets!M:M, All_Tickets!E:E, A17, All_Tickets!J:J, "Closed", All_Tickets!N:N, ">="&EOMONTH(TODAY(),-1)+1, All_Tickets!N:N, "<="&EOMONTH(TODAY(),0)) -> 27
A18: Summit Net Trekker | B18: 100 | C18: 100 | D18: 97 | E18: =D18-SUMIFS(All_Tickets!M:M, All_Tickets!E:E, A18, All_Tickets!J:J, "Closed", All_Tickets!N:N, ">="&EOMONTH(TODAY(),-1)+1, All_Tickets!N:N, "<="&EOMONTH(TODAY(),0)) -> 97
A19: TAT Technologies | B19: 50 | C19: 50 | D19: 47.5 | E19: =D19-SUMIFS(All_Tickets!M:M, All_Tickets!E:E, A19, All_Tickets!J:J, "Closed", All_Tickets!N:N, ">="&EOMONTH(TODAY(),-1)+1, All_Tickets!N:N, "<="&EOMONTH(TODAY(),0)) -> 47.5
A20: Truecare Biomedix | B20: 45 | C20: 34.5 | D20: 27 | E20: =D20-SUMIFS(All_Tickets!M:M, All_Tickets!E:E, A20, All_Tickets!J:J, "Closed", All_Tickets!N:N, ">="&EOMONTH(TODAY(),-1)+1, All_Tickets!N:N, "<="&EOMONTH(TODAY(),0)) -> 23.5
A21: Van Dolder's Home Team | B21: 30.5 | C21: =B21-5.5 -> 25 | D21: 25 | E21: =D21-SUMIFS(All_Tickets!M:M, All_Tickets!E:E, A21, All_Tickets!J:J, "Closed", All_Tickets!N:N, ">="&EOMONTH(TODAY(),-1)+1, All_Tickets!N:N, "<="&EOMONTH(TODAY(),0)) -> 24
A22: Wave Healthcare | B22: 48.5 | C22: 48 | D22: 48 | E22: =D22-SUMIFS(All_Tickets!M:M, All_Tickets!E:E, A22, All_Tickets!J:J, "Closed", All_Tickets!N:N, ">="&EOMONTH(TODAY(),-1)+1, All_Tickets!N:N, "<="&EOMONTH(TODAY(),0)) -> 48
A23: BLUE LABEL PACKAGING CO | B23: 0 | C23: 0 | D23: 49 | E23: =D23-SUMIFS(All_Tickets!M:M, All_Tickets!E:E, A23, All_Tickets!J:J, "Closed", All_Tickets!N:N, ">="&EOMONTH(TODAY(),-1)+1, All_Tickets!N:N, "<="&EOMONTH(TODAY(),0)) -> 49
A24: Aline Studio | B24: 0 | C24: 0 | D24: 50 | E24: =D24-SUMIFS(All_Tickets!M:M, All_Tickets!E:E, A24, All_Tickets!J:J, "Closed", All_Tickets!N:N, ">="&EOMONTH(TODAY(),-1)+1, All_Tickets!N:N, "<="&EOMONTH(TODAY(),0)) -> 49.25

Sheet Hours Used Monthly 
A1: Account Name | B1: Febuary | C1: March
A2: Americal Vision Group | B2: =_xlfn.XLOOKUP(A2,'Balance Hours'!A:A,'Balance Hours'!C:C)-_xlfn.XLOOKUP(A2,'Balance Hours'!A:A,'Balance Hours'!D:D) -> 0 | C2: =SUMIFS(All_Tickets!M:M, All_Tickets!E:E, $A2, All_Tickets!J:J, "Closed", All_Tickets!N:N, ">="&DATE(2026,3,1), All_Tickets!N:N, "<"&DATE(2026,3,31)) -> 0
A3: Anderson and Middleton | B3: =_xlfn.XLOOKUP(A3,'Balance Hours'!A:A,'Balance Hours'!C:C)-_xlfn.XLOOKUP(A3,'Balance Hours'!A:A,'Balance Hours'!D:D) -> 0 | C3: =SUMIFS(All_Tickets!M:M, All_Tickets!E:E, $A3, All_Tickets!J:J, "Closed", All_Tickets!N:N, ">="&DATE(2026,3,1), All_Tickets!N:N, "<"&DATE(2026,3,31)) -> 0
A4: Bahai's Canada | B4: =_xlfn.XLOOKUP(A4,'Balance Hours'!A:A,'Balance Hours'!C:C)-_xlfn.XLOOKUP(A4,'Balance Hours'!A:A,'Balance Hours'!D:D) -> 0 | C4: =SUMIFS(All_Tickets!M:M, All_Tickets!E:E, $A4, All_Tickets!J:J, "Closed", All_Tickets!N:N, ">="&DATE(2026,3,1), All_Tickets!N:N, "<"&DATE(2026,3,31)) -> 0
A5: Buckland | B5: =_xlfn.XLOOKUP(A5,'Balance Hours'!A:A,'Balance Hours'!C:C)-_xlfn.XLOOKUP(A5,'Balance Hours'!A:A,'Balance Hours'!D:D) -> 0 | C5: =SUMIFS(All_Tickets!M:M, All_Tickets!E:E, $A5, All_Tickets!J:J, "Closed", All_Tickets!N:N, ">="&DATE(2026,3,1), All_Tickets!N:N, "<"&DATE(2026,3,31)) -> 0
A6: Centon Electronics | B6: =_xlfn.XLOOKUP(A6,'Balance Hours'!A:A,'Balance Hours'!C:C)-_xlfn.XLOOKUP(A6,'Balance Hours'!A:A,'Balance Hours'!D:D) -> 0 | C6: =SUMIFS(All_Tickets!M:M, All_Tickets!E:E, $A6, All_Tickets!J:J, "Closed", All_Tickets!N:N, ">="&DATE(2026,3,1), All_Tickets!N:N, "<"&DATE(2026,3,31)) -> 0
A7: Child development | B7: 21.5 | C7: =SUMIFS(All_Tickets!M:M, All_Tickets!E:E, $A7, All_Tickets!J:J, "Closed", All_Tickets!N:N, ">="&DATE(2026,3,1), All_Tickets!N:N, "<"&DATE(2026,3,31)) -> 0
A8: F&H Group USA Inc. | B8: =_xlfn.XLOOKUP(A8,'Balance Hours'!A:A,'Balance Hours'!C:C)-_xlfn.XLOOKUP(A8,'Balance Hours'!A:A,'Balance Hours'!D:D) -> 0 | C8: =SUMIFS(All_Tickets!M:M, All_Tickets!E:E, $A8, All_Tickets!J:J, "Closed", All_Tickets!N:N, ">="&DATE(2026,3,1), All_Tickets!N:N, "<"&DATE(2026,3,31)) -> 0
A9: Franken Solar | B9: =_xlfn.XLOOKUP(A9,'Balance Hours'!A:A,'Balance Hours'!C:C)-_xlfn.XLOOKUP(A9,'Balance Hours'!A:A,'Balance Hours'!D:D) -> 1 | C9: =SUMIFS(All_Tickets!M:M, All_Tickets!E:E, $A9, All_Tickets!J:J, "Closed", All_Tickets!N:N, ">="&DATE(2026,3,1), All_Tickets!N:N, "<"&DATE(2026,3,31)) -> 0
A10: Iridex Corporation | B10: =_xlfn.XLOOKUP(A10,'Balance Hours'!A:A,'Balance Hours'!C:C)-_xlfn.XLOOKUP(A10,'Balance Hours'!A:A,'Balance Hours'!D:D) -> 14.75 | C10: =SUMIFS(All_Tickets!M:M, All_Tickets!E:E, $A10, All_Tickets!J:J, "Closed", All_Tickets!N:N, ">="&DATE(2026,3,1), All_Tickets!N:N, "<"&DATE(2026,3,31)) -> 1
A11: Jedwards International, Inc. | B11: =_xlfn.XLOOKUP(A11,'Balance Hours'!A:A,'Balance Hours'!C:C)-_xlfn.XLOOKUP(A11,'Balance Hours'!A:A,'Balance Hours'!D:D) -> 7 | C11: =SUMIFS(All_Tickets!M:M, All_Tickets!E:E, $A11, All_Tickets!J:J, "Closed", All_Tickets!N:N, ">="&DATE(2026,3,1), All_Tickets!N:N, "<"&DATE(2026,3,31)) -> 0
A12: Mexi Land Inc | B12: =_xlfn.XLOOKUP(A12,'Balance Hours'!A:A,'Balance Hours'!C:C)-_xlfn.XLOOKUP(A12,'Balance Hours'!A:A,'Balance Hours'!D:D) -> 1.5 | C12: =SUMIFS(All_Tickets!M:M, All_Tickets!E:E, $A12, All_Tickets!J:J, "Closed", All_Tickets!N:N, ">="&DATE(2026,3,1), All_Tickets!N:N, "<"&DATE(2026,3,31)) -> 0
A13: Microboards Technology | B13: =_xlfn.XLOOKUP(A13,'Balance Hours'!A:A,'Balance Hours'!C:C)-_xlfn.XLOOKUP(A13,'Balance Hours'!A:A,'Balance Hours'!D:D) -> 0 | C13: =SUMIFS(All_Tickets!M:M, All_Tickets!E:E, $A13, All_Tickets!J:J, "Closed", All_Tickets!N:N, ">="&DATE(2026,3,1), All_Tickets!N:N, "<"&DATE(2026,3,31)) -> 0
A14: Millcreek Inn | B14: =_xlfn.XLOOKUP(A14,'Balance Hours'!A:A,'Balance Hours'!C:C)-_xlfn.XLOOKUP(A14,'Balance Hours'!A:A,'Balance Hours'!D:D) -> 1 | C14: =SUMIFS(All_Tickets!M:M, All_Tickets!E:E, $A14, All_Tickets!J:J, "Closed", All_Tickets!N:N, ">="&DATE(2026,3,1), All_Tickets!N:N, "<"&DATE(2026,3,31)) -> 0
A15: Q4 Services Inc. | B15: =_xlfn.XLOOKUP(A15,'Balance Hours'!A:A,'Balance Hours'!C:C)-_xlfn.XLOOKUP(A15,'Balance Hours'!A:A,'Balance Hours'!D:D) -> 3 | C15: =SUMIFS(All_Tickets!M:M, All_Tickets!E:E, $A15, All_Tickets!J:J, "Closed", All_Tickets!N:N, ">="&DATE(2026,3,1), All_Tickets!N:N, "<"&DATE(2026,3,31)) -> 0
A16: Step by Step INC. | B16: =_xlfn.XLOOKUP(A16,'Balance Hours'!A:A,'Balance Hours'!C:C)-_xlfn.XLOOKUP(A16,'Balance Hours'!A:A,'Balance Hours'!D:D) -> 2 | C16: =SUMIFS(All_Tickets!M:M, All_Tickets!E:E, $A16, All_Tickets!J:J, "Closed", All_Tickets!N:N, ">="&DATE(2026,3,1), All_Tickets!N:N, "<"&DATE(2026,3,31)) -> 0
A17: Summit Net Trekker | B17: =_xlfn.XLOOKUP(A17,'Balance Hours'!A:A,'Balance Hours'!C:C)-_xlfn.XLOOKUP(A17,'Balance Hours'!A:A,'Balance Hours'!D:D) -> 3 | C17: =SUMIFS(All_Tickets!M:M, All_Tickets!E:E, $A17, All_Tickets!J:J, "Closed", All_Tickets!N:N, ">="&DATE(2026,3,1), All_Tickets!N:N, "<"&DATE(2026,3,31)) -> 0
A18: TAT Technologies | B18: =_xlfn.XLOOKUP(A18,'Balance Hours'!A:A,'Balance Hours'!C:C)-_xlfn.XLOOKUP(A18,'Balance Hours'!A:A,'Balance Hours'!D:D) -> 2.5 | C18: =SUMIFS(All_Tickets!M:M, All_Tickets!E:E, $A18, All_Tickets!J:J, "Closed", All_Tickets!N:N, ">="&DATE(2026,3,1), All_Tickets!N:N, "<"&DATE(2026,3,31)) -> 0
A19: Truecare Biomedix | B19: =_xlfn.XLOOKUP(A19,'Balance Hours'!A:A,'Balance Hours'!C:C)-_xlfn.XLOOKUP(A19,'Balance Hours'!A:A,'Balance Hours'!D:D) -> 7.5 | C19: =SUMIFS(All_Tickets!M:M, All_Tickets!E:E, $A19, All_Tickets!J:J, "Closed", All_Tickets!N:N, ">="&DATE(2026,3,1), All_Tickets!N:N, "<"&DATE(2026,3,31)) -> 3.5
... A21: Wave Healthcare | B21: =_xlfn.XLOOKUP(A21,'Balance Hours'!A:A,'Balance Hours'!C:C)-_xlfn.XLOOKUP(A21,'Balance Hours'!A:A,'Balance Hours'!D:D) -> 0 | C21: =SUMIFS(All_Tickets!M:M, All_Tickets!E:E, $A21, All_Tickets!J:J, "Closed", All_Tickets!N:N, ">="&DATE(2026,3,1), All_Tickets!N:N, "<"&DATE(2026,3,31)) -> 0
A22: BLUE LABEL PACKAGING CO | B22: 0 | C22: =SUMIFS(All_Tickets!M:M, All_Tickets!E:E, $A22, All_Tickets!J:J, "Closed", All_Tickets!N:N, ">="&DATE(2026,3,1), All_Tickets!N:N, "<"&DATE(2026,3,31)) -> 0
A23: Aline Studio | B23: 0 | C23: =SUMIFS(All_Tickets!M:M, All_Tickets!E:E, $A23, All_Tickets!J:J, "Closed", All_Tickets!N:N, ">="&DATE(2026,3,1), All_Tickets!N:N, "<"&DATE(2026,3,31)) -> 0.75
A24: Total | B24: =SUM(B2:B23) -> 64.75 | C24: =SUM(C2:C23) -> 6.25

Sheet Updates format 
A1: Open Tickets | B1: =COUNTIFS(All_Tickets!J2:J1000,"<>Closed",All_Tickets!J2:J1000,"<>") -> 15
A2: Closed Tickets | B2: =COUNTIFS(All_Tickets!J:J,"Closed",All_Tickets!N:N,TODAY()) -> 0
A3: Feedback Received | B3: 0
A4: Escalation | B4: 0
A5: Meetings | B5: 4
A6: Calls Done | B6: 0

Sheet hiddenSheet
A1: incident:LOKSnd1FareHpei8TkKDPeKa4FC0XhfFxa/4iCtVj5QM8HROurLRaYQpBB7kCou+f8Z0QmOrk5jrUXwjYO13Kg==:incidentid=%28Do%20Not%20Modify%29%20Case&checksumLogicalName=%28Do%20Not%20Modify%29%20Row%20Checksum&modifiedon=%28Do%20Not%20Modify%29%20Modified%20On&ticketnumber=Case%20Number&442bd308-8234-463d-8aca-0eb095fb8874.new_accountdisplayname=Customer%20Name%20%28Customer%29%20%28Account%29&primarycontactid=Contact&createdon=Created%20On&title=Case%20Title&ds_supportagentcontact=Support%20Agent&statuscode=Status%20Reason&prioritycode=Priority&442bd308-8234-463d-8aca-0eb095fb8874.ds_country=Country%20%28Customer%29%20%28Account%29&ds_totalbillableduration=Billable%20Duration
A2: Open | B2: Cancelled | C2: In Progress | D2: Customer Information | E2: Pending for Effort Approval | F2: On Hold | G2: Customer Testing | H2: Move to Prod. | I2: Microsoft | J2: Closed | K2: Problem Solved | L2: Information Provided | M2: Canceled | N2: Merged
A3: High - P1 | B3: Normal - P2 | C3: Low - P3 | D3: P4
